hijack/__init__.py
hijack/_version.py
hijack/apps.py
hijack/conf.py
hijack/forms.py
hijack/middleware.py
hijack/permissions.py
hijack/signals.py
hijack/urls.py
hijack/views.py
hijack/contrib/__init__.py
hijack/contrib/admin/__init__.py
hijack/contrib/admin/admin.py
hijack/contrib/admin/apps.py
hijack/contrib/admin/templates/hijack/contrib/admin/button.html
hijack/locale/cs/LC_MESSAGES/django.mo
hijack/locale/cs/LC_MESSAGES/django.po
hijack/locale/da/LC_MESSAGES/django.mo
hijack/locale/da/LC_MESSAGES/django.po
hijack/locale/de/LC_MESSAGES/django.mo
hijack/locale/de/LC_MESSAGES/django.po
hijack/locale/es/LC_MESSAGES/django.mo
hijack/locale/es/LC_MESSAGES/django.po
hijack/locale/fr/LC_MESSAGES/django.mo
hijack/locale/fr/LC_MESSAGES/django.po
hijack/locale/ja/LC_MESSAGES/django.mo
hijack/locale/ja/LC_MESSAGES/django.po
hijack/locale/nl/LC_MESSAGES/django.mo
hijack/locale/nl/LC_MESSAGES/django.po
hijack/locale/pl/LC_MESSAGES/django.mo
hijack/locale/pl/LC_MESSAGES/django.po
hijack/locale/pt_BR/LC_MESSAGES/django.mo
hijack/locale/pt_BR/LC_MESSAGES/django.po
hijack/locale/ru/LC_MESSAGES/django.mo
hijack/locale/ru/LC_MESSAGES/django.po
hijack/locale/sk/LC_MESSAGES/django.mo
hijack/locale/sk/LC_MESSAGES/django.po
hijack/static/hijack/hijack.css
hijack/static/hijack/hijack.js
hijack/templates/hijack/notification.html
hijack/templatetags/__init__.py
hijack/templatetags/hijack.py
django_hijack-3.7.5.dist-info/licenses/LICENSE
django_hijack-3.7.5.dist-info/WHEEL
django_hijack-3.7.5.dist-info/METADATA
django_hijack-3.7.5.dist-info/RECORD
